kctl/__init__.py
kctl/classes.py
kctl/client.py
kctl/config.py
kctl/logz.py
kctl/static.py
kctl/utils.py
kctl-0.0.1.dist-info/LICENSE
kctl-0.0.1.dist-info/METADATA
kctl-0.0.1.dist-info/WHEEL
kctl-0.0.1.dist-info/top_level.txt
kctl-0.0.1.dist-info/RECORD
