Metadata-Version: 2.1
Name: kctl
Version: 0.0.1
Summary: Rancher Kubernetes API compatible with  RKE, RKE2 and maybe others?
Home-page: https://github.com/trisongz/kctl
Author: Tri Songz
Author-email: ts@growthengineai.com
License: MIT Style
Platform: UNKNOWN
Classifier: Intended Audience :: Developers
Classifier: License :: OSI Approved :: MIT License
Classifier: Programming Language :: Python :: 3.7
Classifier: Topic :: Software Development :: Libraries
License-File: LICENSE
Requires-Dist: lazyapi
Requires-Dist: lazycls
Requires-Dist: kubernetes
